{
    "web-development": {
        "id": 1,
        "urlCode": "web-development",
        "name": "Web Development",
        "heroImage": "https://i.gifer.com/Owm.gif",
        "departmentLeads": [
            {
                "id": 1,
                "memberImage": "https://source.unsplash.com/1w9I6H4aftw",
                "memberName": "Adnan Hashmi",
                "memberStatus": "Core Member",
                "memberAbout": "Hi, I'm Mohit. I like building cool projects and developing artificial inteligence.",
                "memberSocialLinkedinPath": "/",
                "memberSocialGithubPath": "/",
                "memberSocialMailPath": "/"
            },
            {
                "id": 2,
                "memberImage": "https://source.unsplash.com/xd4ao7ALxb0",
                "memberName": "Shubham Rana",
                "memberStatus": "Department Lead",
                "memberAbout": "Hi, I'm Mohit. I like building cool projects and developing artificial inteligence.",
                "memberSocialLinkedinPath": "/",
                "memberSocialGithubPath": "/",
                "memberSocialMailPath": "/"
            }
        ],
        "members": [
            {
                "id": 1,
                "memberImage": "https://source.unsplash.com/1w9I6H4aftw",
                "memberName": "Adnan Hashmi",
                "memberStatus": "Core Member",
                "memberAbout": "Hi, I'm Mohit. I like building cool projects and developing artificial inteligence.",
                "memberSocialLinkedinPath": "/",
                "memberSocialGithubPath": "/",
                "memberSocialMailPath": "/"
            },
            {
                "id": 2,
                "memberImage": "https://source.unsplash.com/xd4ao7ALxb0",
                "memberName": "Shubham Rana",
                "memberStatus": "Department Lead",
                "memberAbout": "Hi, I'm Mohit. I like building cool projects and developing artificial inteligence.",
                "memberSocialLinkedinPath": "/",
                "memberSocialGithubPath": "/",
                "memberSocialMailPath": "/"
            },
            {
                "id": 3,
                "memberImage": "https://source.unsplash.com/1w9I6H4aftw",
                "memberName": "Adnan Hashmi",
                "memberStatus": "Core Member",
                "memberAbout": "Hi, I'm Mohit. I like building cool projects and developing artificial inteligence.",
                "memberSocialLinkedinPath": "/",
                "memberSocialGithubPath": "/",
                "memberSocialMailPath": "/"
            },
            {
                "id": 4,
                "memberImage": "https://source.unsplash.com/xd4ao7ALxb0",
                "memberName": "Shubham Rana",
                "memberStatus": "Department Lead",
                "memberAbout": "Hi, I'm Mohit. I like building cool projects and developing artificial inteligence.",
                "memberSocialLinkedinPath": "/",
                "memberSocialGithubPath": "/",
                "memberSocialMailPath": "/"
            },
            {
                "id": 5,
                "memberImage": "https://source.unsplash.com/1w9I6H4aftw",
                "memberName": "Adnan Hashmi",
                "memberStatus": "Core Member",
                "memberAbout": "Hi, I'm Mohit. I like building cool projects and developing artificial inteligence.",
                "memberSocialLinkedinPath": "/",
                "memberSocialGithubPath": "/",
                "memberSocialMailPath": "/"
            },
            {
                "id": 6,
                "memberImage": "https://source.unsplash.com/xd4ao7ALxb0",
                "memberName": "Shubham Rana",
                "memberStatus": "Department Lead",
                "memberAbout": "Hi, I'm Mohit. I like building cool projects and developing artificial inteligence.",
                "memberSocialLinkedinPath": "/",
                "memberSocialGithubPath": "/",
                "memberSocialMailPath": "/"
            },
            {
                "id": 7,
                "memberImage": "https://source.unsplash.com/1w9I6H4aftw",
                "memberName": "Adnan Hashmi",
                "memberStatus": "Core Member",
                "memberAbout": "Hi, I'm Mohit. I like building cool projects and developing artificial inteligence.",
                "memberSocialLinkedinPath": "/",
                "memberSocialGithubPath": "/",
                "memberSocialMailPath": "/"
            },
            {
                "id": 8,
                "memberImage": "https://source.unsplash.com/xd4ao7ALxb0",
                "memberName": "Shubham Rana",
                "memberStatus": "Department Lead",
                "memberAbout": "Hi, I'm Mohit. I like building cool projects and developing artificial inteligence.",
                "memberSocialLinkedinPath": "/",
                "memberSocialGithubPath": "/",
                "memberSocialMailPath": "/"
            }
        ]
    },
    "app-development": {
        "id": 2,
        "urlCode": "app-development",
        "name": "App Development",
        "heroImage": "https://i.gifer.com/Owm.gif",
        "departmentLeads": {
            "Adnan Hashmi": {
                "id": 1,
                "memberImage": "https://source.unsplash.com/1w9I6H4aftw",
                "memberName": "Adnan Hashmi",
                "memberStatus": "Core Member",
                "memberAbout": "Hi, I'm Mohit. I like building cool projects and developing artificial inteligence.",
                "memberSocialLinkedinPath": "/",
                "memberSocialGithubPath": "/",
                "memberSocialMailPath": "/"
            },
            "Shubham Rana": {
                "id": 2,
                "memberImage": "https://source.unsplash.com/xd4ao7ALxb0",
                "memberName": "Shubham Rana",
                "memberStatus": "Department Lead",
                "memberAbout": "Hi, I'm Mohit. I like building cool projects and developing artificial inteligence.",
                "memberSocialLinkedinPath": "/",
                "memberSocialGithubPath": "/",
                "memberSocialMailPath": "/"
            }
        },
        "members": [
            {
                "id": 1,
                "memberImage": "https://source.unsplash.com/1w9I6H4aftw",
                "memberName": "Adnan Hashmi",
                "memberStatus": "Core Member",
                "memberAbout": "Hi, I'm Mohit. I like building cool projects and developing artificial inteligence.",
                "memberSocialLinkedinPath": "/",
                "memberSocialGithubPath": "/",
                "memberSocialMailPath": "/"
            },
            {
                "id": 2,
                "memberImage": "https://source.unsplash.com/xd4ao7ALxb0",
                "memberName": "Shubham Rana",
                "memberStatus": "Department Lead",
                "memberAbout": "Hi, I'm Mohit. I like building cool projects and developing artificial inteligence.",
                "memberSocialLinkedinPath": "/",
                "memberSocialGithubPath": "/",
                "memberSocialMailPath": "/"
            },
            {
                "id": 3,
                "memberImage": "https://source.unsplash.com/1w9I6H4aftw",
                "memberName": "Adnan Hashmi",
                "memberStatus": "Core Member",
                "memberAbout": "Hi, I'm Mohit. I like building cool projects and developing artificial inteligence.",
                "memberSocialLinkedinPath": "/",
                "memberSocialGithubPath": "/",
                "memberSocialMailPath": "/"
            },
            {
                "id": 4,
                "memberImage": "https://source.unsplash.com/xd4ao7ALxb0",
                "memberName": "Shubham Rana",
                "memberStatus": "Department Lead",
                "memberAbout": "Hi, I'm Mohit. I like building cool projects and developing artificial inteligence.",
                "memberSocialLinkedinPath": "/",
                "memberSocialGithubPath": "/",
                "memberSocialMailPath": "/"
            },
            {
                "id": 5,
                "memberImage": "https://source.unsplash.com/1w9I6H4aftw",
                "memberName": "Adnan Hashmi",
                "memberStatus": "Core Member",
                "memberAbout": "Hi, I'm Mohit. I like building cool projects and developing artificial inteligence.",
                "memberSocialLinkedinPath": "/",
                "memberSocialGithubPath": "/",
                "memberSocialMailPath": "/"
            },
            {
                "id": 6,
                "memberImage": "https://source.unsplash.com/xd4ao7ALxb0",
                "memberName": "Shubham Rana",
                "memberStatus": "Department Lead",
                "memberAbout": "Hi, I'm Mohit. I like building cool projects and developing artificial inteligence.",
                "memberSocialLinkedinPath": "/",
                "memberSocialGithubPath": "/",
                "memberSocialMailPath": "/"
            },
            {
                "id": 7,
                "memberImage": "https://source.unsplash.com/1w9I6H4aftw",
                "memberName": "Adnan Hashmi",
                "memberStatus": "Core Member",
                "memberAbout": "Hi, I'm Mohit. I like building cool projects and developing artificial inteligence.",
                "memberSocialLinkedinPath": "/",
                "memberSocialGithubPath": "/",
                "memberSocialMailPath": "/"
            },
            {
                "id": 8,
                "memberImage": "https://source.unsplash.com/xd4ao7ALxb0",
                "memberName": "Shubham Rana",
                "memberStatus": "Department Lead",
                "memberAbout": "Hi, I'm Mohit. I like building cool projects and developing artificial inteligence.",
                "memberSocialLinkedinPath": "/",
                "memberSocialGithubPath": "/",
                "memberSocialMailPath": "/"
            }
        ]
    },
    "competitive-programming": {
        "id": 3,
        "urlCode": "competitive-programming",
        "name": "Competitive Programming",
        "heroImage": "https://i.gifer.com/Owm.gif",
        "departmentLeads": {
            "Adnan Hashmi": {
                "id": 1,
                "memberImage": "https://source.unsplash.com/1w9I6H4aftw",
                "memberName": "Adnan Hashmi",
                "memberStatus": "Core Member",
                "memberAbout": "Hi, I'm Mohit. I like building cool projects and developing artificial inteligence.",
                "memberSocialLinkedinPath": "/",
                "memberSocialGithubPath": "/",
                "memberSocialMailPath": "/"
            },
            "Shubham Rana": {
                "id": 2,
                "memberImage": "https://source.unsplash.com/xd4ao7ALxb0",
                "memberName": "Shubham Rana",
                "memberStatus": "Department Lead",
                "memberAbout": "Hi, I'm Mohit. I like building cool projects and developing artificial inteligence.",
                "memberSocialLinkedinPath": "/",
                "memberSocialGithubPath": "/",
                "memberSocialMailPath": "/"
            }
        },
        "members": [
            {
                "id": 1,
                "memberImage": "https://source.unsplash.com/1w9I6H4aftw",
                "memberName": "Adnan Hashmi",
                "memberStatus": "Core Member",
                "memberAbout": "Hi, I'm Mohit. I like building cool projects and developing artificial inteligence.",
                "memberSocialLinkedinPath": "/",
                "memberSocialGithubPath": "/",
                "memberSocialMailPath": "/"
            },
            {
                "id": 2,
                "memberImage": "https://source.unsplash.com/xd4ao7ALxb0",
                "memberName": "Shubham Rana",
                "memberStatus": "Department Lead",
                "memberAbout": "Hi, I'm Mohit. I like building cool projects and developing artificial inteligence.",
                "memberSocialLinkedinPath": "/",
                "memberSocialGithubPath": "/",
                "memberSocialMailPath": "/"
            },
            {
                "id": 3,
                "memberImage": "https://source.unsplash.com/1w9I6H4aftw",
                "memberName": "Adnan Hashmi",
                "memberStatus": "Core Member",
                "memberAbout": "Hi, I'm Mohit. I like building cool projects and developing artificial inteligence.",
                "memberSocialLinkedinPath": "/",
                "memberSocialGithubPath": "/",
                "memberSocialMailPath": "/"
            },
            {
                "id": 4,
                "memberImage": "https://source.unsplash.com/xd4ao7ALxb0",
                "memberName": "Shubham Rana",
                "memberStatus": "Department Lead",
                "memberAbout": "Hi, I'm Mohit. I like building cool projects and developing artificial inteligence.",
                "memberSocialLinkedinPath": "/",
                "memberSocialGithubPath": "/",
                "memberSocialMailPath": "/"
            },
            {
                "id": 5,
                "memberImage": "https://source.unsplash.com/1w9I6H4aftw",
                "memberName": "Adnan Hashmi",
                "memberStatus": "Core Member",
                "memberAbout": "Hi, I'm Mohit. I like building cool projects and developing artificial inteligence.",
                "memberSocialLinkedinPath": "/",
                "memberSocialGithubPath": "/",
                "memberSocialMailPath": "/"
            },
            {
                "id": 6,
                "memberImage": "https://source.unsplash.com/xd4ao7ALxb0",
                "memberName": "Shubham Rana",
                "memberStatus": "Department Lead",
                "memberAbout": "Hi, I'm Mohit. I like building cool projects and developing artificial inteligence.",
                "memberSocialLinkedinPath": "/",
                "memberSocialGithubPath": "/",
                "memberSocialMailPath": "/"
            },
            {
                "id": 7,
                "memberImage": "https://source.unsplash.com/1w9I6H4aftw",
                "memberName": "Adnan Hashmi",
                "memberStatus": "Core Member",
                "memberAbout": "Hi, I'm Mohit. I like building cool projects and developing artificial inteligence.",
                "memberSocialLinkedinPath": "/",
                "memberSocialGithubPath": "/",
                "memberSocialMailPath": "/"
            },
            {
                "id": 8,
                "memberImage": "https://source.unsplash.com/xd4ao7ALxb0",
                "memberName": "Shubham Rana",
                "memberStatus": "Department Lead",
                "memberAbout": "Hi, I'm Mohit. I like building cool projects and developing artificial inteligence.",
                "memberSocialLinkedinPath": "/",
                "memberSocialGithubPath": "/",
                "memberSocialMailPath": "/"
            }
        ]
    },
    "machine-learning": {
        "id": 4,
        "urlCode": "machine-learning",
        "name": "Machine Learning",
        "heroImage": "https://i.gifer.com/Owm.gif",
        "departmentLeads": {
            "Adnan Hashmi": {
                "id": 1,
                "memberImage": "https://source.unsplash.com/1w9I6H4aftw",
                "memberName": "Adnan Hashmi",
                "memberStatus": "Core Member",
                "memberAbout": "Hi, I'm Mohit. I like building cool projects and developing artificial inteligence.",
                "memberSocialLinkedinPath": "/",
                "memberSocialGithubPath": "/",
                "memberSocialMailPath": "/"
            },
            "Shubham Rana": {
                "id": 2,
                "memberImage": "https://source.unsplash.com/xd4ao7ALxb0",
                "memberName": "Shubham Rana",
                "memberStatus": "Department Lead",
                "memberAbout": "Hi, I'm Mohit. I like building cool projects and developing artificial inteligence.",
                "memberSocialLinkedinPath": "/",
                "memberSocialGithubPath": "/",
                "memberSocialMailPath": "/"
            }
        },
        "members": [
            {
                "id": 1,
                "memberImage": "https://source.unsplash.com/1w9I6H4aftw",
                "memberName": "Adnan Hashmi",
                "memberStatus": "Core Member",
                "memberAbout": "Hi, I'm Mohit. I like building cool projects and developing artificial inteligence.",
                "memberSocialLinkedinPath": "/",
                "memberSocialGithubPath": "/",
                "memberSocialMailPath": "/"
            },
            {
                "id": 2,
                "memberImage": "https://source.unsplash.com/xd4ao7ALxb0",
                "memberName": "Shubham Rana",
                "memberStatus": "Department Lead",
                "memberAbout": "Hi, I'm Mohit. I like building cool projects and developing artificial inteligence.",
                "memberSocialLinkedinPath": "/",
                "memberSocialGithubPath": "/",
                "memberSocialMailPath": "/"
            },
            {
                "id": 3,
                "memberImage": "https://source.unsplash.com/1w9I6H4aftw",
                "memberName": "Adnan Hashmi",
                "memberStatus": "Core Member",
                "memberAbout": "Hi, I'm Mohit. I like building cool projects and developing artificial inteligence.",
                "memberSocialLinkedinPath": "/",
                "memberSocialGithubPath": "/",
                "memberSocialMailPath": "/"
            },
            {
                "id": 4,
                "memberImage": "https://source.unsplash.com/xd4ao7ALxb0",
                "memberName": "Shubham Rana",
                "memberStatus": "Department Lead",
                "memberAbout": "Hi, I'm Mohit. I like building cool projects and developing artificial inteligence.",
                "memberSocialLinkedinPath": "/",
                "memberSocialGithubPath": "/",
                "memberSocialMailPath": "/"
            },
            {
                "id": 5,
                "memberImage": "https://source.unsplash.com/1w9I6H4aftw",
                "memberName": "Adnan Hashmi",
                "memberStatus": "Core Member",
                "memberAbout": "Hi, I'm Mohit. I like building cool projects and developing artificial inteligence.",
                "memberSocialLinkedinPath": "/",
                "memberSocialGithubPath": "/",
                "memberSocialMailPath": "/"
            },
            {
                "id": 6,
                "memberImage": "https://source.unsplash.com/xd4ao7ALxb0",
                "memberName": "Shubham Rana",
                "memberStatus": "Department Lead",
                "memberAbout": "Hi, I'm Mohit. I like building cool projects and developing artificial inteligence.",
                "memberSocialLinkedinPath": "/",
                "memberSocialGithubPath": "/",
                "memberSocialMailPath": "/"
            },
            {
                "id": 7,
                "memberImage": "https://source.unsplash.com/1w9I6H4aftw",
                "memberName": "Adnan Hashmi",
                "memberStatus": "Core Member",
                "memberAbout": "Hi, I'm Mohit. I like building cool projects and developing artificial inteligence.",
                "memberSocialLinkedinPath": "/",
                "memberSocialGithubPath": "/",
                "memberSocialMailPath": "/"
            },
            {
                "id": 8,
                "memberImage": "https://source.unsplash.com/xd4ao7ALxb0",
                "memberName": "Shubham Rana",
                "memberStatus": "Department Lead",
                "memberAbout": "Hi, I'm Mohit. I like building cool projects and developing artificial inteligence.",
                "memberSocialLinkedinPath": "/",
                "memberSocialGithubPath": "/",
                "memberSocialMailPath": "/"
            }
        ]
    },
    "graphics": {
        "id": 5,
        "urlCode": "graphics",
        "name": "Graphics",
        "heroImage": "https://i.gifer.com/Owm.gif",
        "departmentLeads": {
            "Adnan Hashmi": {
                "id": 1,
                "memberImage": "https://source.unsplash.com/1w9I6H4aftw",
                "memberName": "Adnan Hashmi",
                "memberStatus": "Core Member",
                "memberAbout": "Hi, I'm Mohit. I like building cool projects and developing artificial inteligence.",
                "memberSocialLinkedinPath": "/",
                "memberSocialGithubPath": "/",
                "memberSocialMailPath": "/"
            },
            "Shubham Rana": {
                "id": 2,
                "memberImage": "https://source.unsplash.com/xd4ao7ALxb0",
                "memberName": "Shubham Rana",
                "memberStatus": "Department Lead",
                "memberAbout": "Hi, I'm Mohit. I like building cool projects and developing artificial inteligence.",
                "memberSocialLinkedinPath": "/",
                "memberSocialGithubPath": "/",
                "memberSocialMailPath": "/"
            }
        },
        "members": [
            {
                "id": 1,
                "memberImage": "https://source.unsplash.com/1w9I6H4aftw",
                "memberName": "Adnan Hashmi",
                "memberStatus": "Core Member",
                "memberAbout": "Hi, I'm Mohit. I like building cool projects and developing artificial inteligence.",
                "memberSocialLinkedinPath": "/",
                "memberSocialGithubPath": "/",
                "memberSocialMailPath": "/"
            },
            {
                "id": 2,
                "memberImage": "https://source.unsplash.com/xd4ao7ALxb0",
                "memberName": "Shubham Rana",
                "memberStatus": "Department Lead",
                "memberAbout": "Hi, I'm Mohit. I like building cool projects and developing artificial inteligence.",
                "memberSocialLinkedinPath": "/",
                "memberSocialGithubPath": "/",
                "memberSocialMailPath": "/"
            },
            {
                "id": 3,
                "memberImage": "https://source.unsplash.com/1w9I6H4aftw",
                "memberName": "Adnan Hashmi",
                "memberStatus": "Core Member",
                "memberAbout": "Hi, I'm Mohit. I like building cool projects and developing artificial inteligence.",
                "memberSocialLinkedinPath": "/",
                "memberSocialGithubPath": "/",
                "memberSocialMailPath": "/"
            },
            {
                "id": 4,
                "memberImage": "https://source.unsplash.com/xd4ao7ALxb0",
                "memberName": "Shubham Rana",
                "memberStatus": "Department Lead",
                "memberAbout": "Hi, I'm Mohit. I like building cool projects and developing artificial inteligence.",
                "memberSocialLinkedinPath": "/",
                "memberSocialGithubPath": "/",
                "memberSocialMailPath": "/"
            },
            {
                "id": 5,
                "memberImage": "https://source.unsplash.com/1w9I6H4aftw",
                "memberName": "Adnan Hashmi",
                "memberStatus": "Core Member",
                "memberAbout": "Hi, I'm Mohit. I like building cool projects and developing artificial inteligence.",
                "memberSocialLinkedinPath": "/",
                "memberSocialGithubPath": "/",
                "memberSocialMailPath": "/"
            },
            {
                "id": 6,
                "memberImage": "https://source.unsplash.com/xd4ao7ALxb0",
                "memberName": "Shubham Rana",
                "memberStatus": "Department Lead",
                "memberAbout": "Hi, I'm Mohit. I like building cool projects and developing artificial inteligence.",
                "memberSocialLinkedinPath": "/",
                "memberSocialGithubPath": "/",
                "memberSocialMailPath": "/"
            },
            {
                "id": 7,
                "memberImage": "https://source.unsplash.com/1w9I6H4aftw",
                "memberName": "Adnan Hashmi",
                "memberStatus": "Core Member",
                "memberAbout": "Hi, I'm Mohit. I like building cool projects and developing artificial inteligence.",
                "memberSocialLinkedinPath": "/",
                "memberSocialGithubPath": "/",
                "memberSocialMailPath": "/"
            },
            {
                "id": 8,
                "memberImage": "https://source.unsplash.com/xd4ao7ALxb0",
                "memberName": "Shubham Rana",
                "memberStatus": "Department Lead",
                "memberAbout": "Hi, I'm Mohit. I like building cool projects and developing artificial inteligence.",
                "memberSocialLinkedinPath": "/",
                "memberSocialGithubPath": "/",
                "memberSocialMailPath": "/"
            }
        ]
    },
    "content": {
        "id": 6,
        "urlCode": "content",
        "name": "Content",
        "heroImage": "https://i.gifer.com/Owm.gif",
        "departmentLeads": {
            "Adnan Hashmi": {
                "id": 1,
                "memberImage": "https://source.unsplash.com/1w9I6H4aftw",
                "memberName": "Adnan Hashmi",
                "memberStatus": "Core Member",
                "memberAbout": "Hi, I'm Mohit. I like building cool projects and developing artificial inteligence.",
                "memberSocialLinkedinPath": "/",
                "memberSocialGithubPath": "/",
                "memberSocialMailPath": "/"
            },
            "Shubham Rana": {
                "id": 2,
                "memberImage": "https://source.unsplash.com/xd4ao7ALxb0",
                "memberName": "Shubham Rana",
                "memberStatus": "Department Lead",
                "memberAbout": "Hi, I'm Mohit. I like building cool projects and developing artificial inteligence.",
                "memberSocialLinkedinPath": "/",
                "memberSocialGithubPath": "/",
                "memberSocialMailPath": "/"
            }
        },
        "members": [
            {
                "id": 1,
                "memberImage": "https://source.unsplash.com/1w9I6H4aftw",
                "memberName": "Adnan Hashmi",
                "memberStatus": "Core Member",
                "memberAbout": "Hi, I'm Mohit. I like building cool projects and developing artificial inteligence.",
                "memberSocialLinkedinPath": "/",
                "memberSocialGithubPath": "/",
                "memberSocialMailPath": "/"
            },
            {
                "id": 2,
                "memberImage": "https://source.unsplash.com/xd4ao7ALxb0",
                "memberName": "Shubham Rana",
                "memberStatus": "Department Lead",
                "memberAbout": "Hi, I'm Mohit. I like building cool projects and developing artificial inteligence.",
                "memberSocialLinkedinPath": "/",
                "memberSocialGithubPath": "/",
                "memberSocialMailPath": "/"
            },
            {
                "id": 3,
                "memberImage": "https://source.unsplash.com/1w9I6H4aftw",
                "memberName": "Adnan Hashmi",
                "memberStatus": "Core Member",
                "memberAbout": "Hi, I'm Mohit. I like building cool projects and developing artificial inteligence.",
                "memberSocialLinkedinPath": "/",
                "memberSocialGithubPath": "/",
                "memberSocialMailPath": "/"
            },
            {
                "id": 4,
                "memberImage": "https://source.unsplash.com/xd4ao7ALxb0",
                "memberName": "Shubham Rana",
                "memberStatus": "Department Lead",
                "memberAbout": "Hi, I'm Mohit. I like building cool projects and developing artificial inteligence.",
                "memberSocialLinkedinPath": "/",
                "memberSocialGithubPath": "/",
                "memberSocialMailPath": "/"
            },
            {
                "id": 5,
                "memberImage": "https://source.unsplash.com/1w9I6H4aftw",
                "memberName": "Adnan Hashmi",
                "memberStatus": "Core Member",
                "memberAbout": "Hi, I'm Mohit. I like building cool projects and developing artificial inteligence.",
                "memberSocialLinkedinPath": "/",
                "memberSocialGithubPath": "/",
                "memberSocialMailPath": "/"
            },
            {
                "id": 6,
                "memberImage": "https://source.unsplash.com/xd4ao7ALxb0",
                "memberName": "Shubham Rana",
                "memberStatus": "Department Lead",
                "memberAbout": "Hi, I'm Mohit. I like building cool projects and developing artificial inteligence.",
                "memberSocialLinkedinPath": "/",
                "memberSocialGithubPath": "/",
                "memberSocialMailPath": "/"
            },
            {
                "id": 7,
                "memberImage": "https://source.unsplash.com/1w9I6H4aftw",
                "memberName": "Adnan Hashmi",
                "memberStatus": "Core Member",
                "memberAbout": "Hi, I'm Mohit. I like building cool projects and developing artificial inteligence.",
                "memberSocialLinkedinPath": "/",
                "memberSocialGithubPath": "/",
                "memberSocialMailPath": "/"
            },
            {
                "id": 8,
                "memberImage": "https://source.unsplash.com/xd4ao7ALxb0",
                "memberName": "Shubham Rana",
                "memberStatus": "Department Lead",
                "memberAbout": "Hi, I'm Mohit. I like building cool projects and developing artificial inteligence.",
                "memberSocialLinkedinPath": "/",
                "memberSocialGithubPath": "/",
                "memberSocialMailPath": "/"
            }
        ]
    },
    "operations": {
        "id": 7,
        "urlCode": "operations",
        "name": "Operations",
        "heroImage": "https://i.gifer.com/Owm.gif",
        "departmentLeads": {
            "Adnan Hashmi": {
                "id": 1,
                "memberImage": "https://source.unsplash.com/1w9I6H4aftw",
                "memberName": "Adnan Hashmi",
                "memberStatus": "Core Member",
                "memberAbout": "Hi, I'm Mohit. I like building cool projects and developing artificial inteligence.",
                "memberSocialLinkedinPath": "/",
                "memberSocialGithubPath": "/",
                "memberSocialMailPath": "/"
            },
            "Shubham Rana": {
                "id": 2,
                "memberImage": "https://source.unsplash.com/xd4ao7ALxb0",
                "memberName": "Shubham Rana",
                "memberStatus": "Department Lead",
                "memberAbout": "Hi, I'm Mohit. I like building cool projects and developing artificial inteligence.",
                "memberSocialLinkedinPath": "/",
                "memberSocialGithubPath": "/",
                "memberSocialMailPath": "/"
            }
        },
        "members": [
            {
                "id": 1,
                "memberImage": "https://source.unsplash.com/1w9I6H4aftw",
                "memberName": "Adnan Hashmi",
                "memberStatus": "Core Member",
                "memberAbout": "Hi, I'm Mohit. I like building cool projects and developing artificial inteligence.",
                "memberSocialLinkedinPath": "/",
                "memberSocialGithubPath": "/",
                "memberSocialMailPath": "/"
            },
            {
                "id": 2,
                "memberImage": "https://source.unsplash.com/xd4ao7ALxb0",
                "memberName": "Shubham Rana",
                "memberStatus": "Department Lead",
                "memberAbout": "Hi, I'm Mohit. I like building cool projects and developing artificial inteligence.",
                "memberSocialLinkedinPath": "/",
                "memberSocialGithubPath": "/",
                "memberSocialMailPath": "/"
            },
            {
                "id": 3,
                "memberImage": "https://source.unsplash.com/1w9I6H4aftw",
                "memberName": "Adnan Hashmi",
                "memberStatus": "Core Member",
                "memberAbout": "Hi, I'm Mohit. I like building cool projects and developing artificial inteligence.",
                "memberSocialLinkedinPath": "/",
                "memberSocialGithubPath": "/",
                "memberSocialMailPath": "/"
            },
            {
                "id": 4,
                "memberImage": "https://source.unsplash.com/xd4ao7ALxb0",
                "memberName": "Shubham Rana",
                "memberStatus": "Department Lead",
                "memberAbout": "Hi, I'm Mohit. I like building cool projects and developing artificial inteligence.",
                "memberSocialLinkedinPath": "/",
                "memberSocialGithubPath": "/",
                "memberSocialMailPath": "/"
            },
            {
                "id": 5,
                "memberImage": "https://source.unsplash.com/1w9I6H4aftw",
                "memberName": "Adnan Hashmi",
                "memberStatus": "Core Member",
                "memberAbout": "Hi, I'm Mohit. I like building cool projects and developing artificial inteligence.",
                "memberSocialLinkedinPath": "/",
                "memberSocialGithubPath": "/",
                "memberSocialMailPath": "/"
            },
            {
                "id": 6,
                "memberImage": "https://source.unsplash.com/xd4ao7ALxb0",
                "memberName": "Shubham Rana",
                "memberStatus": "Department Lead",
                "memberAbout": "Hi, I'm Mohit. I like building cool projects and developing artificial inteligence.",
                "memberSocialLinkedinPath": "/",
                "memberSocialGithubPath": "/",
                "memberSocialMailPath": "/"
            },
            {
                "id": 7,
                "memberImage": "https://source.unsplash.com/1w9I6H4aftw",
                "memberName": "Adnan Hashmi",
                "memberStatus": "Core Member",
                "memberAbout": "Hi, I'm Mohit. I like building cool projects and developing artificial inteligence.",
                "memberSocialLinkedinPath": "/",
                "memberSocialGithubPath": "/",
                "memberSocialMailPath": "/"
            },
            {
                "id": 8,
                "memberImage": "https://source.unsplash.com/xd4ao7ALxb0",
                "memberName": "Shubham Rana",
                "memberStatus": "Department Lead",
                "memberAbout": "Hi, I'm Mohit. I like building cool projects and developing artificial inteligence.",
                "memberSocialLinkedinPath": "/",
                "memberSocialGithubPath": "/",
                "memberSocialMailPath": "/"
            }
        ]
    }
}